[
    {
      "company_name": "A.CELLI, Italy",
      "img": "acelli",
      "backContent":"Slitters and Rewinders & Finishing lines for non wovens",
      "backLink":"www.acelli.it/en"
    },
    {
      "company_name": "Buhler Alzenau GmbH, Germany",
      "img": "buhler",
      "backContent":"Vacuum metalizers",
      "backLink":"www.buhlergroup.com"
    },
    {
      "company_name": "IMS Technologies S.P.A., Italy (Goebel IMS, LAEM System, Rotomac)",
      "img": "ims",
      "backContent":"(Goebel IMS, LAEM IMS & ROTOMAC, Slitter & Rewinder",
      "backLink":"www.imstechnologies.com"
    },
    {
      "company_name": "Kroenert GmbH & Co. KG, Germany",
      "img": "kroenert",
      "backContent":"Coating & Laminating Machines",
      "backLink":"www.kroenert.de/en"
    }
  ]
  
